odoo8_addon_l10n_nl_oin-8.0.1.1.0-nspkg.pth
odoo_addons/l10n_nl_oin/README.rst
odoo_addons/l10n_nl_oin/__init__.py
odoo_addons/l10n_nl_oin/__openerp__.py
odoo_addons/l10n_nl_oin/i18n/l10n_nl_oin.pot
odoo_addons/l10n_nl_oin/models/__init__.py
odoo_addons/l10n_nl_oin/models/res_partner.py
odoo_addons/l10n_nl_oin/readme/CONTRIBUTORS.rst
odoo_addons/l10n_nl_oin/readme/DESCRIPTION.rst
odoo_addons/l10n_nl_oin/readme/USAGE.rst
odoo_addons/l10n_nl_oin/static/description/icon.png
odoo_addons/l10n_nl_oin/static/description/index.html
odoo_addons/l10n_nl_oin/tests/__init__.py
odoo_addons/l10n_nl_oin/tests/test_l10n_nl_oin.py
odoo_addons/l10n_nl_oin/views/res_partner.xml
odoo8_addon_l10n_nl_oin-8.0.1.1.0.dist-info/METADATA
odoo8_addon_l10n_nl_oin-8.0.1.1.0.dist-info/WHEEL
odoo8_addon_l10n_nl_oin-8.0.1.1.0.dist-info/namespace_packages.txt
odoo8_addon_l10n_nl_oin-8.0.1.1.0.dist-info/top_level.txt
odoo8_addon_l10n_nl_oin-8.0.1.1.0.dist-info/RECORD
