Metadata-Version: 2.1
Name: odoo8-addon-l10n-nl-oin
Version: 8.0.1.1.0
Summary: Adds Dutch OIN field
Home-page: https://github.com/OCA/l10n-netherlands
Author: Onestein, Odoo Community Association (OCA)
Author-email: support@odoo-community.org
License: AGPL-3
Platform: UNKNOWN
Classifier: Programming Language :: Python
Classifier: Framework :: Odoo
Classifier: License :: OSI Approved :: GNU Affero General Public License v3
Requires-Python: ~=2.7
Requires-Dist: odoo (<9.0a,>=8.0a)
